BangumiAPI/__init__.py
BangumiAPI-0.0.2.dist-info/LICENSE
BangumiAPI-0.0.2.dist-info/METADATA
BangumiAPI-0.0.2.dist-info/WHEEL
BangumiAPI-0.0.2.dist-info/top_level.txt
BangumiAPI-0.0.2.dist-info/RECORD
