Metadata-Version: 2.1
Name: BangumiAPI
Version: 0.0.2
Summary: 番组计划开放API的Python模块
Home-page: https://github.com/WhitePaper233/BangumiAPI
Author: WhitePaper233
Author-email: whitepaper.233@foxmail.com
License: UNKNOWN
Platform: UNKNOWN
Classifier: Programming Language :: Python :: 3.10
Classifier: License :: OSI Approved :: MIT License
Classifier: Operating System :: OS Independent
Requires-Python: >=3.10
License-File: LICENSE
Requires-Dist: requests (>=2.27.1)
